pypownetr/__init__.py
pypownetr/data.py
pypownetr/model.py
pypownetr/solver.py
pypownetr/test_data.py
pypownetr-0.1.0.dist-info/LICENSE
pypownetr-0.1.0.dist-info/METADATA
pypownetr-0.1.0.dist-info/WHEEL
pypownetr-0.1.0.dist-info/top_level.txt
pypownetr-0.1.0.dist-info/RECORD
