Metadata-Version: 2.1
Name: pypownetr
Version: 0.1.0
Summary: Chowdhury et al. PowNet Refactored
Home-page: https://github.com/pacowong/pypownet
Author: pacowong
Author-email: 
License: UNKNOWN
Platform: UNKNOWN
Classifier: Programming Language :: Python :: 3
Classifier: License :: OSI Approved :: MIT License
Classifier: Operating System :: OS Independent
Requires-Python: >=3.6
Requires-Dist: pyomo
Requires-Dist: pandas
